odoo/addons/l10n_mx_cfdi_account/README.rst
odoo/addons/l10n_mx_cfdi_account/__init__.py
odoo/addons/l10n_mx_cfdi_account/__manifest__.py
odoo/addons/l10n_mx_cfdi_account/i18n/es.po
odoo/addons/l10n_mx_cfdi_account/i18n/l10n_mx_cfdi.pot
odoo/addons/l10n_mx_cfdi_account/i18n/l10n_mx_cfdi_account.pot
odoo/addons/l10n_mx_cfdi_account/models/__init__.py
odoo/addons/l10n_mx_cfdi_account/models/account_move.py
odoo/addons/l10n_mx_cfdi_account/models/account_move_line.py
odoo/addons/l10n_mx_cfdi_account/models/account_move_reversal.py
odoo/addons/l10n_mx_cfdi_account/models/account_partial_reconcile.py
odoo/addons/l10n_mx_cfdi_account/models/account_payment.py
odoo/addons/l10n_mx_cfdi_account/models/account_payment_register.py
odoo/addons/l10n_mx_cfdi_account/models/account_tax.py
odoo/addons/l10n_mx_cfdi_account/models/cfdi_document.py
odoo/addons/l10n_mx_cfdi_account/models/res_config_settings.py
odoo/addons/l10n_mx_cfdi_account/readme/CONFIGURE.md
odoo/addons/l10n_mx_cfdi_account/readme/CONTRIBUTORS.md
odoo/addons/l10n_mx_cfdi_account/readme/DESCRIPTION.md
odoo/addons/l10n_mx_cfdi_account/readme/INSTALL.md
odoo/addons/l10n_mx_cfdi_account/readme/ROADMAP.md
odoo/addons/l10n_mx_cfdi_account/readme/USAGE.md
odoo/addons/l10n_mx_cfdi_account/reports/report_external_layouts.xml
odoo/addons/l10n_mx_cfdi_account/reports/report_invoice.xml
odoo/addons/l10n_mx_cfdi_account/reports/report_payment.xml
odoo/addons/l10n_mx_cfdi_account/security/ir.model.access.csv
odoo/addons/l10n_mx_cfdi_account/static/description/icon.png
odoo/addons/l10n_mx_cfdi_account/static/description/icon.svg
odoo/addons/l10n_mx_cfdi_account/static/description/index.html
odoo/addons/l10n_mx_cfdi_account/tests/__init__.py
odoo/addons/l10n_mx_cfdi_account/tests/test_account_move.py
odoo/addons/l10n_mx_cfdi_account/tests/test_account_move_line.py
odoo/addons/l10n_mx_cfdi_account/tests/test_account_payment.py
odoo/addons/l10n_mx_cfdi_account/tests/test_account_tax.py
odoo_addon_l10n_mx_cfdi_account-17.0.1.0.2.dist-info/METADATA
odoo_addon_l10n_mx_cfdi_account-17.0.1.0.2.dist-info/WHEEL
odoo_addon_l10n_mx_cfdi_account-17.0.1.0.2.dist-info/top_level.txt
odoo_addon_l10n_mx_cfdi_account-17.0.1.0.2.dist-info/RECORD
